MANIFEST.in
README.rst
requirements-install.txt
requirements-test.txt
setup.py
chain_bitcoin/__init__.py
chain_bitcoin/chain.pem
chain_bitcoin/chain.py
chain_bitcoin/config.py
chain_bitcoin/endpoints.py
chain_bitcoin/exceptions.py
chain_bitcoin/func_util.py
chain_bitcoin/map_list.py
chain_bitcoin/models.py
chain_bitcoin/namedtuple.py
chain_bitcoin/urls.py
chain_bitcoin.egg-info/PKG-INFO
chain_bitcoin.egg-info/SOURCES.txt
chain_bitcoin.egg-info/dependency_links.txt
chain_bitcoin.egg-info/requires.txt
chain_bitcoin.egg-info/top_level.txt