Metadata-Version: 1.1
Name: chain-bitcoin
Version: 0.4
Summary: Integration library for the Chain.com API
Home-page: https://github.com/cardforcoin/chain-bitcoin-python
Author: Chris Martin
Author-email: ch.martin@gmail.com
License: MIT
Platform: UNKNOWN
Classifier: Intended Audience :: Developers
Classifier: License :: OSI Approved :: MIT License
Classifier: Programming Language :: Python
Classifier: Topic :: Software Development :: Libraries :: Python Modules
Classifier: Programming Language :: Python :: 2.6
Classifier: Programming Language :: Python :: 2.7
Classifier: Programming Language :: Python :: 3.3
Classifier: Programming Language :: Python :: 3.4
